{"legislative_session": "24", "identifier": "HLB 24-35", "title": "To appropriate $16,925 of the Rota Poker License Fee Account under BU 3302; and for other purposes.", "from_organization": "~{\"classification\": \"lower\"}", "classification": ["bill"], "subject": [], "abstracts": [], "other_titles": [], "other_identifiers": [], "actions": [{"description": "Date Introduced", "date": "2025-11-25", "organization_id": "~{\"classification\": \"lower\"}", "classification": ["introduction"], "related_entities": []}, {"description": "House First Reading", "date": "2026-01-20", "organization_id": "~{\"classification\": \"lower\"}", "classification": ["reading-1"], "related_entities": []}, {"description": "House Final Reading", "date": "2026-01-20", "organization_id": "~{\"classification\": \"lower\"}", "classification": ["reading-2"], "related_entities": []}, {"description": "R.L.L. 24-06", "date": "2026-01-27", "organization_id": "~{\"classification\": \"executive\"}", "classification": ["became-law"], "related_entities": []}], "sponsorships": [{"name": "Ogo, JMA", "classification": "primary", "entity_type": "person", "primary": true, "person_id": "~{\"name\": \"Ogo, JMA\"}", "organization_id": null}], "related_bills": [], "versions": [{"note": "HLB 24-35", "links": [{"url": "https://cnmileg.net/documents/house/hse_lb/24/HLB24-35.pdf", "media_type": "application/pdf"}], "date": "", "classification": ""}, {"note": "R.L.L. 24-06", "links": [{"url": "https://cnmileg.net/documents/files/24TH%20UPDATE/RLL%2024-06%20(HLB%2024-35%20To%20appropriate%20%2416%2C925%20of%20the%20Rota%20Poker%20License%20Fee%20Account%20under%20BU%203302%3B%20and%20for%20other%20purposes.).pdf", "media_type": "application/pdf"}], "date": "", "classification": ""}], "documents": [], "citations": [], "sources": [{"url": "https://cnmileg.net/leg_sts.asp?legID=20023&secID=1", "note": ""}], "extras": {}, "jurisdiction": {"id": "ocd-jurisdiction/country:us/territory:mp/government", "name": "Northern Mariana Islands", "classification": "state", "division_id": "ocd-division/country:us/territory:mp"}, "scraped_at": "2026-02-12T08:37:25+00:00", "_id": "0e933f0e-07ee-11f1-b251-2a83752d85f2"}